[
  {
    "index": 0,
    "num": 8842,
    "accessibility": 1,
    "race": "black_poverty"
  },
  {
    "index": 1,
    "num": 8591,
    "accessibility": 1,
    "race": "black_non_poverty"
  },
  {
    "index": 2,
    "num": 260,
    "accessibility": 1,
    "race": "white_poverty"
  },
  {
    "index": 3,
    "num": 461,
    "accessibility": 1,
    "race": "white_non_poverty"
  },
  {
    "index": 4,
    "num": 6225,
    "accessibility": 2,
    "race": "black_poverty"
  },
  {
    "index": 5,
    "num": 10794,
    "accessibility": 2,
    "race": "black_non_poverty"
  },
  {
    "index": 6,
    "num": 809,
    "accessibility": 2,
    "race": "white_poverty"
  },
  {
    "index": 7,
    "num": 997,
    "accessibility": 2,
    "race": "white_non_poverty"
  },
  {
    "index": 8,
    "num": 17256,
    "accessibility": 3,
    "race": "black_poverty"
  },
  {
    "index": 9,
    "num": 35617,
    "accessibility": 3,
    "race": "black_non_poverty"
  },
  {
    "index": 10,
    "num": 1449,
    "accessibility": 3,
    "race": "white_poverty"
  },
  {
    "index": 11,
    "num": 11340,
    "accessibility": 3,
    "race": "white_non_poverty"
  },
  {
    "index": 12,
    "num": 20071,
    "accessibility": 4,
    "race": "black_poverty"
  },
  {
    "index": 13,
    "num": 46334,
    "accessibility": 4,
    "race": "black_non_poverty"
  },
  {
    "index": 14,
    "num": 2813,
    "accessibility": 4,
    "race": "white_poverty"
  },
  {
    "index": 15,
    "num": 12000,
    "accessibility": 4,
    "race": "white_non_poverty"
  },
  {
    "index": 16,
    "num": 13320,
    "accessibility": 5,
    "race": "black_poverty"
  },
  {
    "index": 17,
    "num": 36969,
    "accessibility": 5,
    "race": "black_non_poverty"
  },
  {
    "index": 18,
    "num": 1868,
    "accessibility": 5,
    "race": "white_poverty"
  },
  {
    "index": 19,
    "num": 12436,
    "accessibility": 5,
    "race": "white_non_poverty"
  },
  {
    "index": 20,
    "num": 13829,
    "accessibility": 6,
    "race": "black_poverty"
  },
  {
    "index": 21,
    "num": 53334,
    "accessibility": 6,
    "race": "black_non_poverty"
  },
  {
    "index": 22,
    "num": 3936,
    "accessibility": 6,
    "race": "white_poverty"
  },
  {
    "index": 23,
    "num": 23174,
    "accessibility": 6,
    "race": "white_non_poverty"
  },
  {
    "index": 24,
    "num": 10932,
    "accessibility": 7,
    "race": "black_poverty"
  },
  {
    "index": 25,
    "num": 45044,
    "accessibility": 7,
    "race": "black_non_poverty"
  },
  {
    "index": 26,
    "num": 4489,
    "accessibility": 7,
    "race": "white_poverty"
  },
  {
    "index": 27,
    "num": 38314,
    "accessibility": 7,
    "race": "white_non_poverty"
  },
  {
    "index": 28,
    "num": 6288,
    "accessibility": 8,
    "race": "black_poverty"
  },
  {
    "index": 29,
    "num": 40528,
    "accessibility": 8,
    "race": "black_non_poverty"
  },
  {
    "index": 30,
    "num": 4123,
    "accessibility": 8,
    "race": "white_poverty"
  },
  {
    "index": 31,
    "num": 37184,
    "accessibility": 8,
    "race": "white_non_poverty"
  },
  {
    "index": 32,
    "num": 4756,
    "accessibility": 9,
    "race": "black_poverty"
  },
  {
    "index": 33,
    "num": 38656,
    "accessibility": 9,
    "race": "black_non_poverty"
  },
  {
    "index": 34,
    "num": 5619,
    "accessibility": 9,
    "race": "white_poverty"
  },
  {
    "index": 35,
    "num": 66087,
    "accessibility": 9,
    "race": "white_non_poverty"
  },
  {
    "index": 36,
    "num": 2743,
    "accessibility": 10,
    "race": "black_poverty"
  },
  {
    "index": 37,
    "num": 17160,
    "accessibility": 10,
    "race": "black_non_poverty"
  },
  {
    "index": 38,
    "num": 5302,
    "accessibility": 10,
    "race": "white_poverty"
  },
  {
    "index": 39,
    "num": 73816,
    "accessibility": 10,
    "race": "white_non_poverty"
  }
]