[
  {
    "index": 0,
    "num": 83,
    "accessibility": 1,
    "race": "white_poverty",
    "label": "health_acc_score"
  },
  {
    "index": 1,
    "num": 1212,
    "accessibility": 1,
    "race": "white_non_poverty",
    "label": "health_acc_score"
  },
  {
    "index": 2,
    "num": 49,
    "accessibility": 2,
    "race": "black_poverty",
    "label": "health_acc_score"
  },
  {
    "index": 3,
    "num": 835,
    "accessibility": 2,
    "race": "black_non_poverty",
    "label": "health_acc_score"
  },
  {
    "index": 4,
    "num": 708,
    "accessibility": 2,
    "race": "white_poverty",
    "label": "health_acc_score"
  },
  {
    "index": 5,
    "num": 7281,
    "accessibility": 2,
    "race": "white_non_poverty",
    "label": "health_acc_score"
  },
  {
    "index": 6,
    "num": 2020,
    "accessibility": 3,
    "race": "black_poverty",
    "label": "health_acc_score"
  },
  {
    "index": 7,
    "num": 2022,
    "accessibility": 3,
    "race": "black_non_poverty",
    "label": "health_acc_score"
  },
  {
    "index": 8,
    "num": 464,
    "accessibility": 3,
    "race": "white_poverty",
    "label": "health_acc_score"
  },
  {
    "index": 9,
    "num": 3590,
    "accessibility": 3,
    "race": "white_non_poverty",
    "label": "health_acc_score"
  },
  {
    "index": 10,
    "num": 12248,
    "accessibility": 4,
    "race": "black_poverty",
    "label": "health_acc_score"
  },
  {
    "index": 11,
    "num": 17271,
    "accessibility": 4,
    "race": "black_non_poverty",
    "label": "health_acc_score"
  },
  {
    "index": 12,
    "num": 1164,
    "accessibility": 4,
    "race": "white_poverty",
    "label": "health_acc_score"
  },
  {
    "index": 13,
    "num": 9730,
    "accessibility": 4,
    "race": "white_non_poverty",
    "label": "health_acc_score"
  },
  {
    "index": 14,
    "num": 8443,
    "accessibility": 5,
    "race": "black_poverty",
    "label": "health_acc_score"
  },
  {
    "index": 15,
    "num": 16254,
    "accessibility": 5,
    "race": "black_non_poverty",
    "label": "health_acc_score"
  },
  {
    "index": 16,
    "num": 947,
    "accessibility": 5,
    "race": "white_poverty",
    "label": "health_acc_score"
  },
  {
    "index": 17,
    "num": 11869,
    "accessibility": 5,
    "race": "white_non_poverty",
    "label": "health_acc_score"
  },
  {
    "index": 18,
    "num": 5300,
    "accessibility": 6,
    "race": "black_poverty",
    "label": "health_acc_score"
  },
  {
    "index": 19,
    "num": 9053,
    "accessibility": 6,
    "race": "black_non_poverty",
    "label": "health_acc_score"
  },
  {
    "index": 20,
    "num": 741,
    "accessibility": 6,
    "race": "white_poverty",
    "label": "health_acc_score"
  },
  {
    "index": 21,
    "num": 2794,
    "accessibility": 6,
    "race": "white_non_poverty",
    "label": "health_acc_score"
  },
  {
    "index": 22,
    "num": 5202,
    "accessibility": 7,
    "race": "black_poverty",
    "label": "health_acc_score"
  },
  {
    "index": 23,
    "num": 12089,
    "accessibility": 7,
    "race": "black_non_poverty",
    "label": "health_acc_score"
  },
  {
    "index": 24,
    "num": 281,
    "accessibility": 7,
    "race": "white_poverty",
    "label": "health_acc_score"
  },
  {
    "index": 25,
    "num": 1598,
    "accessibility": 7,
    "race": "white_non_poverty",
    "label": "health_acc_score"
  },
  {
    "index": 26,
    "num": 4424,
    "accessibility": 8,
    "race": "black_poverty",
    "label": "health_acc_score"
  },
  {
    "index": 27,
    "num": 10262,
    "accessibility": 8,
    "race": "black_non_poverty",
    "label": "health_acc_score"
  },
  {
    "index": 28,
    "num": 1824,
    "accessibility": 8,
    "race": "white_poverty",
    "label": "health_acc_score"
  },
  {
    "index": 29,
    "num": 15018,
    "accessibility": 8,
    "race": "white_non_poverty",
    "label": "health_acc_score"
  },
  {
    "index": 30,
    "num": 706,
    "accessibility": 9,
    "race": "black_poverty",
    "label": "health_acc_score"
  },
  {
    "index": 31,
    "num": 2608,
    "accessibility": 9,
    "race": "black_non_poverty",
    "label": "health_acc_score"
  },
  {
    "index": 32,
    "num": 1837,
    "accessibility": 9,
    "race": "white_poverty",
    "label": "health_acc_score"
  },
  {
    "index": 33,
    "num": 11132,
    "accessibility": 9,
    "race": "white_non_poverty",
    "label": "health_acc_score"
  },
  {
    "index": 34,
    "num": 878,
    "accessibility": 10,
    "race": "black_poverty",
    "label": "health_acc_score"
  },
  {
    "index": 35,
    "num": 5169,
    "accessibility": 10,
    "race": "black_non_poverty",
    "label": "health_acc_score"
  },
  {
    "index": 36,
    "num": 2412,
    "accessibility": 10,
    "race": "white_poverty",
    "label": "health_acc_score"
  },
  {
    "index": 37,
    "num": 28888,
    "accessibility": 10,
    "race": "white_non_poverty",
    "label": "health_acc_score"
  },
  {
    "index": 0,
    "num": 83,
    "accessibility": 1,
    "race": "white_poverty",
    "label": "health2_acc_score"
  },
  {
    "index": 1,
    "num": 1212,
    "accessibility": 1,
    "race": "white_non_poverty",
    "label": "health2_acc_score"
  },
  {
    "index": 2,
    "num": 49,
    "accessibility": 2,
    "race": "black_poverty",
    "label": "health2_acc_score"
  },
  {
    "index": 3,
    "num": 835,
    "accessibility": 2,
    "race": "black_non_poverty",
    "label": "health2_acc_score"
  },
  {
    "index": 4,
    "num": 708,
    "accessibility": 2,
    "race": "white_poverty",
    "label": "health2_acc_score"
  },
  {
    "index": 5,
    "num": 7281,
    "accessibility": 2,
    "race": "white_non_poverty",
    "label": "health2_acc_score"
  },
  {
    "index": 6,
    "num": 2020,
    "accessibility": 3,
    "race": "black_poverty",
    "label": "health2_acc_score"
  },
  {
    "index": 7,
    "num": 2022,
    "accessibility": 3,
    "race": "black_non_poverty",
    "label": "health2_acc_score"
  },
  {
    "index": 8,
    "num": 464,
    "accessibility": 3,
    "race": "white_poverty",
    "label": "health2_acc_score"
  },
  {
    "index": 9,
    "num": 3590,
    "accessibility": 3,
    "race": "white_non_poverty",
    "label": "health2_acc_score"
  },
  {
    "index": 10,
    "num": 12210,
    "accessibility": 4,
    "race": "black_poverty",
    "label": "health2_acc_score"
  },
  {
    "index": 11,
    "num": 17145,
    "accessibility": 4,
    "race": "black_non_poverty",
    "label": "health2_acc_score"
  },
  {
    "index": 12,
    "num": 1139,
    "accessibility": 4,
    "race": "white_poverty",
    "label": "health2_acc_score"
  },
  {
    "index": 13,
    "num": 9692,
    "accessibility": 4,
    "race": "white_non_poverty",
    "label": "health2_acc_score"
  },
  {
    "index": 14,
    "num": 8463,
    "accessibility": 5,
    "race": "black_poverty",
    "label": "health2_acc_score"
  },
  {
    "index": 15,
    "num": 16217,
    "accessibility": 5,
    "race": "black_non_poverty",
    "label": "health2_acc_score"
  },
  {
    "index": 16,
    "num": 972,
    "accessibility": 5,
    "race": "white_poverty",
    "label": "health2_acc_score"
  },
  {
    "index": 17,
    "num": 9614,
    "accessibility": 5,
    "race": "white_non_poverty",
    "label": "health2_acc_score"
  },
  {
    "index": 18,
    "num": 3704,
    "accessibility": 6,
    "race": "black_poverty",
    "label": "health2_acc_score"
  },
  {
    "index": 19,
    "num": 6099,
    "accessibility": 6,
    "race": "black_non_poverty",
    "label": "health2_acc_score"
  },
  {
    "index": 20,
    "num": 290,
    "accessibility": 6,
    "race": "white_poverty",
    "label": "health2_acc_score"
  },
  {
    "index": 21,
    "num": 4006,
    "accessibility": 6,
    "race": "white_non_poverty",
    "label": "health2_acc_score"
  },
  {
    "index": 22,
    "num": 5637,
    "accessibility": 7,
    "race": "black_poverty",
    "label": "health2_acc_score"
  },
  {
    "index": 23,
    "num": 10312,
    "accessibility": 7,
    "race": "black_non_poverty",
    "label": "health2_acc_score"
  },
  {
    "index": 24,
    "num": 628,
    "accessibility": 7,
    "race": "white_poverty",
    "label": "health2_acc_score"
  },
  {
    "index": 25,
    "num": 2257,
    "accessibility": 7,
    "race": "white_non_poverty",
    "label": "health2_acc_score"
  },
  {
    "index": 26,
    "num": 5431,
    "accessibility": 8,
    "race": "black_poverty",
    "label": "health2_acc_score"
  },
  {
    "index": 27,
    "num": 13980,
    "accessibility": 8,
    "race": "black_non_poverty",
    "label": "health2_acc_score"
  },
  {
    "index": 28,
    "num": 1035,
    "accessibility": 8,
    "race": "white_poverty",
    "label": "health2_acc_score"
  },
  {
    "index": 29,
    "num": 8015,
    "accessibility": 8,
    "race": "white_non_poverty",
    "label": "health2_acc_score"
  },
  {
    "index": 30,
    "num": 693,
    "accessibility": 9,
    "race": "black_poverty",
    "label": "health2_acc_score"
  },
  {
    "index": 31,
    "num": 2714,
    "accessibility": 9,
    "race": "black_non_poverty",
    "label": "health2_acc_score"
  },
  {
    "index": 32,
    "num": 1713,
    "accessibility": 9,
    "race": "white_poverty",
    "label": "health2_acc_score"
  },
  {
    "index": 33,
    "num": 14071,
    "accessibility": 9,
    "race": "white_non_poverty",
    "label": "health2_acc_score"
  },
  {
    "index": 34,
    "num": 1063,
    "accessibility": 10,
    "race": "black_poverty",
    "label": "health2_acc_score"
  },
  {
    "index": 35,
    "num": 6239,
    "accessibility": 10,
    "race": "black_non_poverty",
    "label": "health2_acc_score"
  },
  {
    "index": 36,
    "num": 3429,
    "accessibility": 10,
    "race": "white_poverty",
    "label": "health2_acc_score"
  },
  {
    "index": 37,
    "num": 33374,
    "accessibility": 10,
    "race": "white_non_poverty",
    "label": "health2_acc_score"
  },
  {
    "index": 0,
    "num": 2069,
    "accessibility": 1,
    "race": "black_poverty",
    "label": "health2_Monday_score"
  },
  {
    "index": 1,
    "num": 2857,
    "accessibility": 1,
    "race": "black_non_poverty",
    "label": "health2_Monday_score"
  },
  {
    "index": 2,
    "num": 1255,
    "accessibility": 1,
    "race": "white_poverty",
    "label": "health2_Monday_score"
  },
  {
    "index": 3,
    "num": 12083,
    "accessibility": 1,
    "race": "white_non_poverty",
    "label": "health2_Monday_score"
  },
  {
    "index": 4,
    "num": 13113,
    "accessibility": 2,
    "race": "black_poverty",
    "label": "health2_Monday_score"
  },
  {
    "index": 5,
    "num": 19268,
    "accessibility": 2,
    "race": "black_non_poverty",
    "label": "health2_Monday_score"
  },
  {
    "index": 6,
    "num": 1429,
    "accessibility": 2,
    "race": "white_poverty",
    "label": "health2_Monday_score"
  },
  {
    "index": 7,
    "num": 12657,
    "accessibility": 2,
    "race": "white_non_poverty",
    "label": "health2_Monday_score"
  },
  {
    "index": 8,
    "num": 11264,
    "accessibility": 3,
    "race": "black_poverty",
    "label": "health2_Monday_score"
  },
  {
    "index": 9,
    "num": 20193,
    "accessibility": 3,
    "race": "black_non_poverty",
    "label": "health2_Monday_score"
  },
  {
    "index": 10,
    "num": 972,
    "accessibility": 3,
    "race": "white_poverty",
    "label": "health2_Monday_score"
  },
  {
    "index": 11,
    "num": 10655,
    "accessibility": 3,
    "race": "white_non_poverty",
    "label": "health2_Monday_score"
  },
  {
    "index": 12,
    "num": 5637,
    "accessibility": 4,
    "race": "black_poverty",
    "label": "health2_Monday_score"
  },
  {
    "index": 13,
    "num": 10312,
    "accessibility": 4,
    "race": "black_non_poverty",
    "label": "health2_Monday_score"
  },
  {
    "index": 14,
    "num": 628,
    "accessibility": 4,
    "race": "white_poverty",
    "label": "health2_Monday_score"
  },
  {
    "index": 15,
    "num": 2257,
    "accessibility": 4,
    "race": "white_non_poverty",
    "label": "health2_Monday_score"
  },
  {
    "index": 16,
    "num": 5102,
    "accessibility": 5,
    "race": "black_poverty",
    "label": "health2_Monday_score"
  },
  {
    "index": 17,
    "num": 13950,
    "accessibility": 5,
    "race": "black_non_poverty",
    "label": "health2_Monday_score"
  },
  {
    "index": 18,
    "num": 1045,
    "accessibility": 5,
    "race": "white_poverty",
    "label": "health2_Monday_score"
  },
  {
    "index": 19,
    "num": 8962,
    "accessibility": 5,
    "race": "white_non_poverty",
    "label": "health2_Monday_score"
  },
  {
    "index": 20,
    "num": 734,
    "accessibility": 6,
    "race": "black_poverty",
    "label": "health2_Monday_score"
  },
  {
    "index": 21,
    "num": 2369,
    "accessibility": 6,
    "race": "black_non_poverty",
    "label": "health2_Monday_score"
  },
  {
    "index": 22,
    "num": 1210,
    "accessibility": 6,
    "race": "white_poverty",
    "label": "health2_Monday_score"
  },
  {
    "index": 23,
    "num": 8105,
    "accessibility": 6,
    "race": "white_non_poverty",
    "label": "health2_Monday_score"
  },
  {
    "index": 24,
    "num": 492,
    "accessibility": 7,
    "race": "black_poverty",
    "label": "health2_Monday_score"
  },
  {
    "index": 25,
    "num": 1636,
    "accessibility": 7,
    "race": "black_non_poverty",
    "label": "health2_Monday_score"
  },
  {
    "index": 26,
    "num": 1589,
    "accessibility": 7,
    "race": "white_poverty",
    "label": "health2_Monday_score"
  },
  {
    "index": 27,
    "num": 10301,
    "accessibility": 7,
    "race": "white_non_poverty",
    "label": "health2_Monday_score"
  },
  {
    "index": 28,
    "num": 645,
    "accessibility": 8,
    "race": "black_poverty",
    "label": "health2_Monday_score"
  },
  {
    "index": 29,
    "num": 2191,
    "accessibility": 8,
    "race": "black_non_poverty",
    "label": "health2_Monday_score"
  },
  {
    "index": 30,
    "num": 863,
    "accessibility": 8,
    "race": "white_poverty",
    "label": "health2_Monday_score"
  },
  {
    "index": 31,
    "num": 10987,
    "accessibility": 8,
    "race": "white_non_poverty",
    "label": "health2_Monday_score"
  },
  {
    "index": 32,
    "num": 168,
    "accessibility": 9,
    "race": "black_poverty",
    "label": "health2_Monday_score"
  },
  {
    "index": 33,
    "num": 1579,
    "accessibility": 9,
    "race": "black_non_poverty",
    "label": "health2_Monday_score"
  },
  {
    "index": 34,
    "num": 1364,
    "accessibility": 9,
    "race": "white_poverty",
    "label": "health2_Monday_score"
  },
  {
    "index": 35,
    "num": 13581,
    "accessibility": 9,
    "race": "white_non_poverty",
    "label": "health2_Monday_score"
  },
  {
    "index": 36,
    "num": 46,
    "accessibility": 10,
    "race": "black_poverty",
    "label": "health2_Monday_score"
  },
  {
    "index": 37,
    "num": 1208,
    "accessibility": 10,
    "race": "black_non_poverty",
    "label": "health2_Monday_score"
  },
  {
    "index": 38,
    "num": 106,
    "accessibility": 10,
    "race": "white_poverty",
    "label": "health2_Monday_score"
  },
  {
    "index": 39,
    "num": 3524,
    "accessibility": 10,
    "race": "white_non_poverty",
    "label": "health2_Monday_score"
  },
  {
    "index": 0,
    "num": 6479,
    "accessibility": 1,
    "race": "black_poverty",
    "label": "health2_compete2_score"
  },
  {
    "index": 1,
    "num": 9090,
    "accessibility": 1,
    "race": "black_non_poverty",
    "label": "health2_compete2_score"
  },
  {
    "index": 2,
    "num": 1923,
    "accessibility": 1,
    "race": "white_poverty",
    "label": "health2_compete2_score"
  },
  {
    "index": 3,
    "num": 20071,
    "accessibility": 1,
    "race": "white_non_poverty",
    "label": "health2_compete2_score"
  },
  {
    "index": 4,
    "num": 19652,
    "accessibility": 2,
    "race": "black_poverty",
    "label": "health2_compete2_score"
  },
  {
    "index": 5,
    "num": 31840,
    "accessibility": 2,
    "race": "black_non_poverty",
    "label": "health2_compete2_score"
  },
  {
    "index": 6,
    "num": 1767,
    "accessibility": 2,
    "race": "white_poverty",
    "label": "health2_compete2_score"
  },
  {
    "index": 7,
    "num": 13141,
    "accessibility": 2,
    "race": "white_non_poverty",
    "label": "health2_compete2_score"
  },
  {
    "index": 8,
    "num": 8949,
    "accessibility": 3,
    "race": "black_poverty",
    "label": "health2_compete2_score"
  },
  {
    "index": 9,
    "num": 22382,
    "accessibility": 3,
    "race": "black_non_poverty",
    "label": "health2_compete2_score"
  },
  {
    "index": 10,
    "num": 1595,
    "accessibility": 3,
    "race": "white_poverty",
    "label": "health2_compete2_score"
  },
  {
    "index": 11,
    "num": 13681,
    "accessibility": 3,
    "race": "white_non_poverty",
    "label": "health2_compete2_score"
  },
  {
    "index": 12,
    "num": 2469,
    "accessibility": 4,
    "race": "black_poverty",
    "label": "health2_compete2_score"
  },
  {
    "index": 13,
    "num": 5015,
    "accessibility": 4,
    "race": "black_non_poverty",
    "label": "health2_compete2_score"
  },
  {
    "index": 14,
    "num": 1214,
    "accessibility": 4,
    "race": "white_poverty",
    "label": "health2_compete2_score"
  },
  {
    "index": 15,
    "num": 9217,
    "accessibility": 4,
    "race": "white_non_poverty",
    "label": "health2_compete2_score"
  },
  {
    "index": 16,
    "num": 1444,
    "accessibility": 5,
    "race": "black_poverty",
    "label": "health2_compete2_score"
  },
  {
    "index": 17,
    "num": 3633,
    "accessibility": 5,
    "race": "black_non_poverty",
    "label": "health2_compete2_score"
  },
  {
    "index": 18,
    "num": 1890,
    "accessibility": 5,
    "race": "white_poverty",
    "label": "health2_compete2_score"
  },
  {
    "index": 19,
    "num": 11280,
    "accessibility": 5,
    "race": "white_non_poverty",
    "label": "health2_compete2_score"
  },
  {
    "index": 20,
    "num": 75,
    "accessibility": 6,
    "race": "black_poverty",
    "label": "health2_compete2_score"
  },
  {
    "index": 21,
    "num": 1694,
    "accessibility": 6,
    "race": "black_non_poverty",
    "label": "health2_compete2_score"
  },
  {
    "index": 22,
    "num": 877,
    "accessibility": 6,
    "race": "white_poverty",
    "label": "health2_compete2_score"
  },
  {
    "index": 23,
    "num": 12351,
    "accessibility": 6,
    "race": "white_non_poverty",
    "label": "health2_compete2_score"
  },
  {
    "index": 24,
    "num": 156,
    "accessibility": 7,
    "race": "black_poverty",
    "label": "health2_compete2_score"
  },
  {
    "index": 25,
    "num": 1233,
    "accessibility": 7,
    "race": "black_non_poverty",
    "label": "health2_compete2_score"
  },
  {
    "index": 26,
    "num": 1089,
    "accessibility": 7,
    "race": "white_poverty",
    "label": "health2_compete2_score"
  },
  {
    "index": 27,
    "num": 9965,
    "accessibility": 7,
    "race": "white_non_poverty",
    "label": "health2_compete2_score"
  },
  {
    "index": 28,
    "num": 46,
    "accessibility": 8,
    "race": "black_poverty",
    "label": "health2_compete2_score"
  },
  {
    "index": 29,
    "num": 676,
    "accessibility": 8,
    "race": "black_non_poverty",
    "label": "health2_compete2_score"
  },
  {
    "index": 30,
    "num": 106,
    "accessibility": 8,
    "race": "white_poverty",
    "label": "health2_compete2_score"
  },
  {
    "index": 31,
    "num": 3406,
    "accessibility": 8,
    "race": "white_non_poverty",
    "label": "health2_compete2_score"
  },
  {
    "index": 0,
    "num": 6479,
    "accessibility": 1,
    "race": "black_poverty",
    "label": "health2_compete1.5_score"
  },
  {
    "index": 1,
    "num": 9090,
    "accessibility": 1,
    "race": "black_non_poverty",
    "label": "health2_compete1.5_score"
  },
  {
    "index": 2,
    "num": 1923,
    "accessibility": 1,
    "race": "white_poverty",
    "label": "health2_compete1.5_score"
  },
  {
    "index": 3,
    "num": 20071,
    "accessibility": 1,
    "race": "white_non_poverty",
    "label": "health2_compete1.5_score"
  },
  {
    "index": 4,
    "num": 21923,
    "accessibility": 2,
    "race": "black_poverty",
    "label": "health2_compete1.5_score"
  },
  {
    "index": 5,
    "num": 35750,
    "accessibility": 2,
    "race": "black_non_poverty",
    "label": "health2_compete1.5_score"
  },
  {
    "index": 6,
    "num": 2237,
    "accessibility": 2,
    "race": "white_poverty",
    "label": "health2_compete1.5_score"
  },
  {
    "index": 7,
    "num": 14069,
    "accessibility": 2,
    "race": "white_non_poverty",
    "label": "health2_compete1.5_score"
  },
  {
    "index": 8,
    "num": 6841,
    "accessibility": 3,
    "race": "black_poverty",
    "label": "health2_compete1.5_score"
  },
  {
    "index": 9,
    "num": 19018,
    "accessibility": 3,
    "race": "black_non_poverty",
    "label": "health2_compete1.5_score"
  },
  {
    "index": 10,
    "num": 1679,
    "accessibility": 3,
    "race": "white_poverty",
    "label": "health2_compete1.5_score"
  },
  {
    "index": 11,
    "num": 16240,
    "accessibility": 3,
    "race": "white_non_poverty",
    "label": "health2_compete1.5_score"
  },
  {
    "index": 12,
    "num": 2999,
    "accessibility": 4,
    "race": "black_poverty",
    "label": "health2_compete1.5_score"
  },
  {
    "index": 13,
    "num": 6080,
    "accessibility": 4,
    "race": "black_non_poverty",
    "label": "health2_compete1.5_score"
  },
  {
    "index": 14,
    "num": 1791,
    "accessibility": 4,
    "race": "white_poverty",
    "label": "health2_compete1.5_score"
  },
  {
    "index": 15,
    "num": 12750,
    "accessibility": 4,
    "race": "white_non_poverty",
    "label": "health2_compete1.5_score"
  },
  {
    "index": 16,
    "num": 826,
    "accessibility": 5,
    "race": "black_poverty",
    "label": "health2_compete1.5_score"
  },
  {
    "index": 17,
    "num": 3072,
    "accessibility": 5,
    "race": "black_non_poverty",
    "label": "health2_compete1.5_score"
  },
  {
    "index": 18,
    "num": 1471,
    "accessibility": 5,
    "race": "white_poverty",
    "label": "health2_compete1.5_score"
  },
  {
    "index": 19,
    "num": 14591,
    "accessibility": 5,
    "race": "white_non_poverty",
    "label": "health2_compete1.5_score"
  },
  {
    "index": 20,
    "num": 108,
    "accessibility": 6,
    "race": "black_poverty",
    "label": "health2_compete1.5_score"
  },
  {
    "index": 21,
    "num": 1298,
    "accessibility": 6,
    "race": "black_non_poverty",
    "label": "health2_compete1.5_score"
  },
  {
    "index": 22,
    "num": 993,
    "accessibility": 6,
    "race": "white_poverty",
    "label": "health2_compete1.5_score"
  },
  {
    "index": 23,
    "num": 9265,
    "accessibility": 6,
    "race": "white_non_poverty",
    "label": "health2_compete1.5_score"
  },
  {
    "index": 24,
    "num": 94,
    "accessibility": 7,
    "race": "black_poverty",
    "label": "health2_compete1.5_score"
  },
  {
    "index": 25,
    "num": 1255,
    "accessibility": 7,
    "race": "black_non_poverty",
    "label": "health2_compete1.5_score"
  },
  {
    "index": 26,
    "num": 367,
    "accessibility": 7,
    "race": "white_poverty",
    "label": "health2_compete1.5_score"
  },
  {
    "index": 27,
    "num": 6126,
    "accessibility": 7,
    "race": "white_non_poverty",
    "label": "health2_compete1.5_score"
  },
  {
    "index": 0,
    "num": 83,
    "accessibility": 1,
    "race": "white_poverty",
    "label": "food_acc_score"
  },
  {
    "index": 1,
    "num": 1212,
    "accessibility": 1,
    "race": "white_non_poverty",
    "label": "food_acc_score"
  },
  {
    "index": 2,
    "num": 6,
    "accessibility": 3,
    "race": "black_poverty",
    "label": "food_acc_score"
  },
  {
    "index": 3,
    "num": 198,
    "accessibility": 3,
    "race": "black_non_poverty",
    "label": "food_acc_score"
  },
  {
    "index": 4,
    "num": 352,
    "accessibility": 3,
    "race": "white_poverty",
    "label": "food_acc_score"
  },
  {
    "index": 5,
    "num": 4207,
    "accessibility": 3,
    "race": "white_non_poverty",
    "label": "food_acc_score"
  },
  {
    "index": 6,
    "num": 73,
    "accessibility": 4,
    "race": "black_poverty",
    "label": "food_acc_score"
  },
  {
    "index": 7,
    "num": 675,
    "accessibility": 4,
    "race": "black_non_poverty",
    "label": "food_acc_score"
  },
  {
    "index": 8,
    "num": 476,
    "accessibility": 4,
    "race": "white_poverty",
    "label": "food_acc_score"
  },
  {
    "index": 9,
    "num": 4561,
    "accessibility": 4,
    "race": "white_non_poverty",
    "label": "food_acc_score"
  },
  {
    "index": 10,
    "num": 6306,
    "accessibility": 5,
    "race": "black_poverty",
    "label": "food_acc_score"
  },
  {
    "index": 11,
    "num": 7790,
    "accessibility": 5,
    "race": "black_non_poverty",
    "label": "food_acc_score"
  },
  {
    "index": 12,
    "num": 657,
    "accessibility": 5,
    "race": "white_poverty",
    "label": "food_acc_score"
  },
  {
    "index": 13,
    "num": 4343,
    "accessibility": 5,
    "race": "white_non_poverty",
    "label": "food_acc_score"
  },
  {
    "index": 14,
    "num": 7473,
    "accessibility": 6,
    "race": "black_poverty",
    "label": "food_acc_score"
  },
  {
    "index": 15,
    "num": 10085,
    "accessibility": 6,
    "race": "black_non_poverty",
    "label": "food_acc_score"
  },
  {
    "index": 16,
    "num": 815,
    "accessibility": 6,
    "race": "white_poverty",
    "label": "food_acc_score"
  },
  {
    "index": 17,
    "num": 9899,
    "accessibility": 6,
    "race": "white_non_poverty",
    "label": "food_acc_score"
  },
  {
    "index": 18,
    "num": 4939,
    "accessibility": 7,
    "race": "black_poverty",
    "label": "food_acc_score"
  },
  {
    "index": 19,
    "num": 11610,
    "accessibility": 7,
    "race": "black_non_poverty",
    "label": "food_acc_score"
  },
  {
    "index": 20,
    "num": 1269,
    "accessibility": 7,
    "race": "white_poverty",
    "label": "food_acc_score"
  },
  {
    "index": 21,
    "num": 9583,
    "accessibility": 7,
    "race": "white_non_poverty",
    "label": "food_acc_score"
  },
  {
    "index": 22,
    "num": 5317,
    "accessibility": 8,
    "race": "black_poverty",
    "label": "food_acc_score"
  },
  {
    "index": 23,
    "num": 9493,
    "accessibility": 8,
    "race": "black_non_poverty",
    "label": "food_acc_score"
  },
  {
    "index": 24,
    "num": 458,
    "accessibility": 8,
    "race": "white_poverty",
    "label": "food_acc_score"
  },
  {
    "index": 25,
    "num": 4420,
    "accessibility": 8,
    "race": "white_non_poverty",
    "label": "food_acc_score"
  },
  {
    "index": 26,
    "num": 9700,
    "accessibility": 9,
    "race": "black_poverty",
    "label": "food_acc_score"
  },
  {
    "index": 27,
    "num": 19247,
    "accessibility": 9,
    "race": "black_non_poverty",
    "label": "food_acc_score"
  },
  {
    "index": 28,
    "num": 1560,
    "accessibility": 9,
    "race": "white_poverty",
    "label": "food_acc_score"
  },
  {
    "index": 29,
    "num": 12134,
    "accessibility": 9,
    "race": "white_non_poverty",
    "label": "food_acc_score"
  },
  {
    "index": 30,
    "num": 5456,
    "accessibility": 10,
    "race": "black_poverty",
    "label": "food_acc_score"
  },
  {
    "index": 31,
    "num": 16465,
    "accessibility": 10,
    "race": "black_non_poverty",
    "label": "food_acc_score"
  },
  {
    "index": 32,
    "num": 4791,
    "accessibility": 10,
    "race": "white_poverty",
    "label": "food_acc_score"
  },
  {
    "index": 33,
    "num": 42753,
    "accessibility": 10,
    "race": "white_non_poverty",
    "label": "food_acc_score"
  },
  {
    "index": 0,
    "num": 83,
    "accessibility": 1,
    "race": "white_poverty",
    "label": "food2_acc_score"
  },
  {
    "index": 1,
    "num": 1212,
    "accessibility": 1,
    "race": "white_non_poverty",
    "label": "food2_acc_score"
  },
  {
    "index": 2,
    "num": 6,
    "accessibility": 3,
    "race": "black_poverty",
    "label": "food2_acc_score"
  },
  {
    "index": 3,
    "num": 363,
    "accessibility": 3,
    "race": "black_non_poverty",
    "label": "food2_acc_score"
  },
  {
    "index": 4,
    "num": 361,
    "accessibility": 3,
    "race": "white_poverty",
    "label": "food2_acc_score"
  },
  {
    "index": 5,
    "num": 4463,
    "accessibility": 3,
    "race": "white_non_poverty",
    "label": "food2_acc_score"
  },
  {
    "index": 6,
    "num": 73,
    "accessibility": 4,
    "race": "black_poverty",
    "label": "food2_acc_score"
  },
  {
    "index": 7,
    "num": 510,
    "accessibility": 4,
    "race": "black_non_poverty",
    "label": "food2_acc_score"
  },
  {
    "index": 8,
    "num": 467,
    "accessibility": 4,
    "race": "white_poverty",
    "label": "food2_acc_score"
  },
  {
    "index": 9,
    "num": 4305,
    "accessibility": 4,
    "race": "white_non_poverty",
    "label": "food2_acc_score"
  },
  {
    "index": 10,
    "num": 6306,
    "accessibility": 5,
    "race": "black_poverty",
    "label": "food2_acc_score"
  },
  {
    "index": 11,
    "num": 7790,
    "accessibility": 5,
    "race": "black_non_poverty",
    "label": "food2_acc_score"
  },
  {
    "index": 12,
    "num": 657,
    "accessibility": 5,
    "race": "white_poverty",
    "label": "food2_acc_score"
  },
  {
    "index": 13,
    "num": 4343,
    "accessibility": 5,
    "race": "white_non_poverty",
    "label": "food2_acc_score"
  },
  {
    "index": 14,
    "num": 8655,
    "accessibility": 6,
    "race": "black_poverty",
    "label": "food2_acc_score"
  },
  {
    "index": 15,
    "num": 13597,
    "accessibility": 6,
    "race": "black_non_poverty",
    "label": "food2_acc_score"
  },
  {
    "index": 16,
    "num": 986,
    "accessibility": 6,
    "race": "white_poverty",
    "label": "food2_acc_score"
  },
  {
    "index": 17,
    "num": 10181,
    "accessibility": 6,
    "race": "white_non_poverty",
    "label": "food2_acc_score"
  },
  {
    "index": 18,
    "num": 7243,
    "accessibility": 7,
    "race": "black_poverty",
    "label": "food2_acc_score"
  },
  {
    "index": 19,
    "num": 13037,
    "accessibility": 7,
    "race": "black_non_poverty",
    "label": "food2_acc_score"
  },
  {
    "index": 20,
    "num": 1063,
    "accessibility": 7,
    "race": "white_poverty",
    "label": "food2_acc_score"
  },
  {
    "index": 21,
    "num": 8581,
    "accessibility": 7,
    "race": "white_non_poverty",
    "label": "food2_acc_score"
  },
  {
    "index": 22,
    "num": 4704,
    "accessibility": 8,
    "race": "black_poverty",
    "label": "food2_acc_score"
  },
  {
    "index": 23,
    "num": 8690,
    "accessibility": 8,
    "race": "black_non_poverty",
    "label": "food2_acc_score"
  },
  {
    "index": 24,
    "num": 652,
    "accessibility": 8,
    "race": "white_poverty",
    "label": "food2_acc_score"
  },
  {
    "index": 25,
    "num": 6151,
    "accessibility": 8,
    "race": "white_non_poverty",
    "label": "food2_acc_score"
  },
  {
    "index": 26,
    "num": 6975,
    "accessibility": 9,
    "race": "black_poverty",
    "label": "food2_acc_score"
  },
  {
    "index": 27,
    "num": 16238,
    "accessibility": 9,
    "race": "black_non_poverty",
    "label": "food2_acc_score"
  },
  {
    "index": 28,
    "num": 1597,
    "accessibility": 9,
    "race": "white_poverty",
    "label": "food2_acc_score"
  },
  {
    "index": 29,
    "num": 14612,
    "accessibility": 9,
    "race": "white_non_poverty",
    "label": "food2_acc_score"
  },
  {
    "index": 30,
    "num": 5308,
    "accessibility": 10,
    "race": "black_poverty",
    "label": "food2_acc_score"
  },
  {
    "index": 31,
    "num": 15338,
    "accessibility": 10,
    "race": "black_non_poverty",
    "label": "food2_acc_score"
  },
  {
    "index": 32,
    "num": 4595,
    "accessibility": 10,
    "race": "white_poverty",
    "label": "food2_acc_score"
  },
  {
    "index": 33,
    "num": 39264,
    "accessibility": 10,
    "race": "white_non_poverty",
    "label": "food2_acc_score"
  },
  {
    "index": 0,
    "num": 15,
    "accessibility": 1,
    "race": "black_poverty",
    "label": "food2_Monday_score"
  },
  {
    "index": 1,
    "num": 561,
    "accessibility": 1,
    "race": "black_non_poverty",
    "label": "food2_Monday_score"
  },
  {
    "index": 2,
    "num": 535,
    "accessibility": 1,
    "race": "white_poverty",
    "label": "food2_Monday_score"
  },
  {
    "index": 3,
    "num": 7425,
    "accessibility": 1,
    "race": "white_non_poverty",
    "label": "food2_Monday_score"
  },
  {
    "index": 4,
    "num": 3967,
    "accessibility": 2,
    "race": "black_poverty",
    "label": "food2_Monday_score"
  },
  {
    "index": 5,
    "num": 3710,
    "accessibility": 2,
    "race": "black_non_poverty",
    "label": "food2_Monday_score"
  },
  {
    "index": 6,
    "num": 480,
    "accessibility": 2,
    "race": "white_poverty",
    "label": "food2_Monday_score"
  },
  {
    "index": 7,
    "num": 2561,
    "accessibility": 2,
    "race": "white_non_poverty",
    "label": "food2_Monday_score"
  },
  {
    "index": 8,
    "num": 2509,
    "accessibility": 3,
    "race": "black_poverty",
    "label": "food2_Monday_score"
  },
  {
    "index": 9,
    "num": 4403,
    "accessibility": 3,
    "race": "black_non_poverty",
    "label": "food2_Monday_score"
  },
  {
    "index": 10,
    "num": 585,
    "accessibility": 3,
    "race": "white_poverty",
    "label": "food2_Monday_score"
  },
  {
    "index": 11,
    "num": 4416,
    "accessibility": 3,
    "race": "white_non_poverty",
    "label": "food2_Monday_score"
  },
  {
    "index": 12,
    "num": 8719,
    "accessibility": 4,
    "race": "black_poverty",
    "label": "food2_Monday_score"
  },
  {
    "index": 13,
    "num": 13444,
    "accessibility": 4,
    "race": "black_non_poverty",
    "label": "food2_Monday_score"
  },
  {
    "index": 14,
    "num": 815,
    "accessibility": 4,
    "race": "white_poverty",
    "label": "food2_Monday_score"
  },
  {
    "index": 15,
    "num": 10005,
    "accessibility": 4,
    "race": "white_non_poverty",
    "label": "food2_Monday_score"
  },
  {
    "index": 16,
    "num": 3520,
    "accessibility": 5,
    "race": "black_poverty",
    "label": "food2_Monday_score"
  },
  {
    "index": 17,
    "num": 5392,
    "accessibility": 5,
    "race": "black_non_poverty",
    "label": "food2_Monday_score"
  },
  {
    "index": 18,
    "num": 269,
    "accessibility": 5,
    "race": "white_poverty",
    "label": "food2_Monday_score"
  },
  {
    "index": 19,
    "num": 938,
    "accessibility": 5,
    "race": "white_non_poverty",
    "label": "food2_Monday_score"
  },
  {
    "index": 20,
    "num": 4610,
    "accessibility": 6,
    "race": "black_poverty",
    "label": "food2_Monday_score"
  },
  {
    "index": 21,
    "num": 9846,
    "accessibility": 6,
    "race": "black_non_poverty",
    "label": "food2_Monday_score"
  },
  {
    "index": 22,
    "num": 755,
    "accessibility": 6,
    "race": "white_poverty",
    "label": "food2_Monday_score"
  },
  {
    "index": 23,
    "num": 7385,
    "accessibility": 6,
    "race": "white_non_poverty",
    "label": "food2_Monday_score"
  },
  {
    "index": 24,
    "num": 5537,
    "accessibility": 7,
    "race": "black_poverty",
    "label": "food2_Monday_score"
  },
  {
    "index": 25,
    "num": 9890,
    "accessibility": 7,
    "race": "black_non_poverty",
    "label": "food2_Monday_score"
  },
  {
    "index": 26,
    "num": 1074,
    "accessibility": 7,
    "race": "white_poverty",
    "label": "food2_Monday_score"
  },
  {
    "index": 27,
    "num": 6689,
    "accessibility": 7,
    "race": "white_non_poverty",
    "label": "food2_Monday_score"
  },
  {
    "index": 28,
    "num": 4701,
    "accessibility": 8,
    "race": "black_poverty",
    "label": "food2_Monday_score"
  },
  {
    "index": 29,
    "num": 11765,
    "accessibility": 8,
    "race": "black_non_poverty",
    "label": "food2_Monday_score"
  },
  {
    "index": 30,
    "num": 646,
    "accessibility": 8,
    "race": "white_poverty",
    "label": "food2_Monday_score"
  },
  {
    "index": 31,
    "num": 4384,
    "accessibility": 8,
    "race": "white_non_poverty",
    "label": "food2_Monday_score"
  },
  {
    "index": 32,
    "num": 4533,
    "accessibility": 9,
    "race": "black_poverty",
    "label": "food2_Monday_score"
  },
  {
    "index": 33,
    "num": 9926,
    "accessibility": 9,
    "race": "black_non_poverty",
    "label": "food2_Monday_score"
  },
  {
    "index": 34,
    "num": 1736,
    "accessibility": 9,
    "race": "white_poverty",
    "label": "food2_Monday_score"
  },
  {
    "index": 35,
    "num": 18577,
    "accessibility": 9,
    "race": "white_non_poverty",
    "label": "food2_Monday_score"
  },
  {
    "index": 36,
    "num": 1159,
    "accessibility": 10,
    "race": "black_poverty",
    "label": "food2_Monday_score"
  },
  {
    "index": 37,
    "num": 6626,
    "accessibility": 10,
    "race": "black_non_poverty",
    "label": "food2_Monday_score"
  },
  {
    "index": 38,
    "num": 3566,
    "accessibility": 10,
    "race": "white_poverty",
    "label": "food2_Monday_score"
  },
  {
    "index": 39,
    "num": 30732,
    "accessibility": 10,
    "race": "white_non_poverty",
    "label": "food2_Monday_score"
  },
  {
    "index": 0,
    "num": 2888,
    "accessibility": 1,
    "race": "black_poverty",
    "label": "food2_compete2_score"
  },
  {
    "index": 1,
    "num": 5220,
    "accessibility": 1,
    "race": "black_non_poverty",
    "label": "food2_compete2_score"
  },
  {
    "index": 2,
    "num": 1736,
    "accessibility": 1,
    "race": "white_poverty",
    "label": "food2_compete2_score"
  },
  {
    "index": 3,
    "num": 17992,
    "accessibility": 1,
    "race": "white_non_poverty",
    "label": "food2_compete2_score"
  },
  {
    "index": 4,
    "num": 15350,
    "accessibility": 2,
    "race": "black_poverty",
    "label": "food2_compete2_score"
  },
  {
    "index": 5,
    "num": 21840,
    "accessibility": 2,
    "race": "black_non_poverty",
    "label": "food2_compete2_score"
  },
  {
    "index": 6,
    "num": 1614,
    "accessibility": 2,
    "race": "white_poverty",
    "label": "food2_compete2_score"
  },
  {
    "index": 7,
    "num": 13275,
    "accessibility": 2,
    "race": "white_non_poverty",
    "label": "food2_compete2_score"
  },
  {
    "index": 8,
    "num": 11723,
    "accessibility": 3,
    "race": "black_poverty",
    "label": "food2_compete2_score"
  },
  {
    "index": 9,
    "num": 21638,
    "accessibility": 3,
    "race": "black_non_poverty",
    "label": "food2_compete2_score"
  },
  {
    "index": 10,
    "num": 873,
    "accessibility": 3,
    "race": "white_poverty",
    "label": "food2_compete2_score"
  },
  {
    "index": 11,
    "num": 6115,
    "accessibility": 3,
    "race": "white_non_poverty",
    "label": "food2_compete2_score"
  },
  {
    "index": 12,
    "num": 4104,
    "accessibility": 4,
    "race": "black_poverty",
    "label": "food2_compete2_score"
  },
  {
    "index": 13,
    "num": 13055,
    "accessibility": 4,
    "race": "black_non_poverty",
    "label": "food2_compete2_score"
  },
  {
    "index": 14,
    "num": 1306,
    "accessibility": 4,
    "race": "white_poverty",
    "label": "food2_compete2_score"
  },
  {
    "index": 15,
    "num": 12558,
    "accessibility": 4,
    "race": "white_non_poverty",
    "label": "food2_compete2_score"
  },
  {
    "index": 16,
    "num": 4051,
    "accessibility": 5,
    "race": "black_poverty",
    "label": "food2_compete2_score"
  },
  {
    "index": 17,
    "num": 7707,
    "accessibility": 5,
    "race": "black_non_poverty",
    "label": "food2_compete2_score"
  },
  {
    "index": 18,
    "num": 2179,
    "accessibility": 5,
    "race": "white_poverty",
    "label": "food2_compete2_score"
  },
  {
    "index": 19,
    "num": 12095,
    "accessibility": 5,
    "race": "white_non_poverty",
    "label": "food2_compete2_score"
  },
  {
    "index": 20,
    "num": 813,
    "accessibility": 6,
    "race": "black_poverty",
    "label": "food2_compete2_score"
  },
  {
    "index": 21,
    "num": 2745,
    "accessibility": 6,
    "race": "black_non_poverty",
    "label": "food2_compete2_score"
  },
  {
    "index": 22,
    "num": 1107,
    "accessibility": 6,
    "race": "white_poverty",
    "label": "food2_compete2_score"
  },
  {
    "index": 23,
    "num": 12786,
    "accessibility": 6,
    "race": "white_non_poverty",
    "label": "food2_compete2_score"
  },
  {
    "index": 24,
    "num": 242,
    "accessibility": 7,
    "race": "black_poverty",
    "label": "food2_compete2_score"
  },
  {
    "index": 25,
    "num": 2248,
    "accessibility": 7,
    "race": "black_non_poverty",
    "label": "food2_compete2_score"
  },
  {
    "index": 26,
    "num": 1286,
    "accessibility": 7,
    "race": "white_poverty",
    "label": "food2_compete2_score"
  },
  {
    "index": 27,
    "num": 13219,
    "accessibility": 7,
    "race": "white_non_poverty",
    "label": "food2_compete2_score"
  },
  {
    "index": 28,
    "num": 99,
    "accessibility": 8,
    "race": "black_poverty",
    "label": "food2_compete2_score"
  },
  {
    "index": 29,
    "num": 1110,
    "accessibility": 8,
    "race": "black_non_poverty",
    "label": "food2_compete2_score"
  },
  {
    "index": 30,
    "num": 360,
    "accessibility": 8,
    "race": "white_poverty",
    "label": "food2_compete2_score"
  },
  {
    "index": 31,
    "num": 5072,
    "accessibility": 8,
    "race": "white_non_poverty",
    "label": "food2_compete2_score"
  },
  {
    "index": 0,
    "num": 5119,
    "accessibility": 1,
    "race": "black_poverty",
    "label": "food2_compete1.5_score"
  },
  {
    "index": 1,
    "num": 7037,
    "accessibility": 1,
    "race": "black_non_poverty",
    "label": "food2_compete1.5_score"
  },
  {
    "index": 2,
    "num": 1915,
    "accessibility": 1,
    "race": "white_poverty",
    "label": "food2_compete1.5_score"
  },
  {
    "index": 3,
    "num": 20051,
    "accessibility": 1,
    "race": "white_non_poverty",
    "label": "food2_compete1.5_score"
  },
  {
    "index": 4,
    "num": 16462,
    "accessibility": 2,
    "race": "black_poverty",
    "label": "food2_compete1.5_score"
  },
  {
    "index": 5,
    "num": 28933,
    "accessibility": 2,
    "race": "black_non_poverty",
    "label": "food2_compete1.5_score"
  },
  {
    "index": 6,
    "num": 1564,
    "accessibility": 2,
    "race": "white_poverty",
    "label": "food2_compete1.5_score"
  },
  {
    "index": 7,
    "num": 14560,
    "accessibility": 2,
    "race": "white_non_poverty",
    "label": "food2_compete1.5_score"
  },
  {
    "index": 8,
    "num": 9336,
    "accessibility": 3,
    "race": "black_poverty",
    "label": "food2_compete1.5_score"
  },
  {
    "index": 9,
    "num": 13722,
    "accessibility": 3,
    "race": "black_non_poverty",
    "label": "food2_compete1.5_score"
  },
  {
    "index": 10,
    "num": 932,
    "accessibility": 3,
    "race": "white_poverty",
    "label": "food2_compete1.5_score"
  },
  {
    "index": 11,
    "num": 4509,
    "accessibility": 3,
    "race": "white_non_poverty",
    "label": "food2_compete1.5_score"
  },
  {
    "index": 12,
    "num": 4832,
    "accessibility": 4,
    "race": "black_poverty",
    "label": "food2_compete1.5_score"
  },
  {
    "index": 13,
    "num": 15197,
    "accessibility": 4,
    "race": "black_non_poverty",
    "label": "food2_compete1.5_score"
  },
  {
    "index": 14,
    "num": 2234,
    "accessibility": 4,
    "race": "white_poverty",
    "label": "food2_compete1.5_score"
  },
  {
    "index": 15,
    "num": 17558,
    "accessibility": 4,
    "race": "white_non_poverty",
    "label": "food2_compete1.5_score"
  },
  {
    "index": 16,
    "num": 2750,
    "accessibility": 5,
    "race": "black_poverty",
    "label": "food2_compete1.5_score"
  },
  {
    "index": 17,
    "num": 6381,
    "accessibility": 5,
    "race": "black_non_poverty",
    "label": "food2_compete1.5_score"
  },
  {
    "index": 18,
    "num": 1852,
    "accessibility": 5,
    "race": "white_poverty",
    "label": "food2_compete1.5_score"
  },
  {
    "index": 19,
    "num": 13333,
    "accessibility": 5,
    "race": "white_non_poverty",
    "label": "food2_compete1.5_score"
  },
  {
    "index": 20,
    "num": 578,
    "accessibility": 6,
    "race": "black_poverty",
    "label": "food2_compete1.5_score"
  },
  {
    "index": 21,
    "num": 1522,
    "accessibility": 6,
    "race": "black_non_poverty",
    "label": "food2_compete1.5_score"
  },
  {
    "index": 22,
    "num": 806,
    "accessibility": 6,
    "race": "white_poverty",
    "label": "food2_compete1.5_score"
  },
  {
    "index": 23,
    "num": 9197,
    "accessibility": 6,
    "race": "white_non_poverty",
    "label": "food2_compete1.5_score"
  },
  {
    "index": 24,
    "num": 167,
    "accessibility": 7,
    "race": "black_poverty",
    "label": "food2_compete1.5_score"
  },
  {
    "index": 25,
    "num": 2648,
    "accessibility": 7,
    "race": "black_non_poverty",
    "label": "food2_compete1.5_score"
  },
  {
    "index": 26,
    "num": 1055,
    "accessibility": 7,
    "race": "white_poverty",
    "label": "food2_compete1.5_score"
  },
  {
    "index": 27,
    "num": 13420,
    "accessibility": 7,
    "race": "white_non_poverty",
    "label": "food2_compete1.5_score"
  },
  {
    "index": 28,
    "num": 26,
    "accessibility": 8,
    "race": "black_poverty",
    "label": "food2_compete1.5_score"
  },
  {
    "index": 29,
    "num": 123,
    "accessibility": 8,
    "race": "black_non_poverty",
    "label": "food2_compete1.5_score"
  },
  {
    "index": 30,
    "num": 103,
    "accessibility": 8,
    "race": "white_poverty",
    "label": "food2_compete1.5_score"
  },
  {
    "index": 31,
    "num": 484,
    "accessibility": 8,
    "race": "white_non_poverty",
    "label": "food2_compete1.5_score"
  },
  {
    "index": 0,
    "num": 83,
    "accessibility": 1,
    "race": "white_poverty",
    "label": "grocery_acc_score"
  },
  {
    "index": 1,
    "num": 1212,
    "accessibility": 1,
    "race": "white_non_poverty",
    "label": "grocery_acc_score"
  },
  {
    "index": 2,
    "num": 69,
    "accessibility": 2,
    "race": "white_poverty",
    "label": "grocery_acc_score"
  },
  {
    "index": 3,
    "num": 531,
    "accessibility": 2,
    "race": "white_non_poverty",
    "label": "grocery_acc_score"
  },
  {
    "index": 4,
    "num": 49,
    "accessibility": 3,
    "race": "black_poverty",
    "label": "grocery_acc_score"
  },
  {
    "index": 5,
    "num": 835,
    "accessibility": 3,
    "race": "black_non_poverty",
    "label": "grocery_acc_score"
  },
  {
    "index": 6,
    "num": 663,
    "accessibility": 3,
    "race": "white_poverty",
    "label": "grocery_acc_score"
  },
  {
    "index": 7,
    "num": 7873,
    "accessibility": 3,
    "race": "white_non_poverty",
    "label": "grocery_acc_score"
  },
  {
    "index": 8,
    "num": 2020,
    "accessibility": 4,
    "race": "black_poverty",
    "label": "grocery_acc_score"
  },
  {
    "index": 9,
    "num": 2022,
    "accessibility": 4,
    "race": "black_non_poverty",
    "label": "grocery_acc_score"
  },
  {
    "index": 10,
    "num": 440,
    "accessibility": 4,
    "race": "white_poverty",
    "label": "grocery_acc_score"
  },
  {
    "index": 11,
    "num": 2467,
    "accessibility": 4,
    "race": "white_non_poverty",
    "label": "grocery_acc_score"
  },
  {
    "index": 12,
    "num": 5570,
    "accessibility": 5,
    "race": "black_poverty",
    "label": "grocery_acc_score"
  },
  {
    "index": 13,
    "num": 8372,
    "accessibility": 5,
    "race": "black_non_poverty",
    "label": "grocery_acc_score"
  },
  {
    "index": 14,
    "num": 887,
    "accessibility": 5,
    "race": "white_poverty",
    "label": "grocery_acc_score"
  },
  {
    "index": 15,
    "num": 11272,
    "accessibility": 5,
    "race": "white_non_poverty",
    "label": "grocery_acc_score"
  },
  {
    "index": 16,
    "num": 9699,
    "accessibility": 6,
    "race": "black_poverty",
    "label": "grocery_acc_score"
  },
  {
    "index": 17,
    "num": 15396,
    "accessibility": 6,
    "race": "black_non_poverty",
    "label": "grocery_acc_score"
  },
  {
    "index": 18,
    "num": 1343,
    "accessibility": 6,
    "race": "white_poverty",
    "label": "grocery_acc_score"
  },
  {
    "index": 19,
    "num": 8996,
    "accessibility": 6,
    "race": "white_non_poverty",
    "label": "grocery_acc_score"
  },
  {
    "index": 20,
    "num": 7141,
    "accessibility": 7,
    "race": "black_poverty",
    "label": "grocery_acc_score"
  },
  {
    "index": 21,
    "num": 14044,
    "accessibility": 7,
    "race": "black_non_poverty",
    "label": "grocery_acc_score"
  },
  {
    "index": 22,
    "num": 738,
    "accessibility": 7,
    "race": "white_poverty",
    "label": "grocery_acc_score"
  },
  {
    "index": 23,
    "num": 6715,
    "accessibility": 7,
    "race": "white_non_poverty",
    "label": "grocery_acc_score"
  },
  {
    "index": 24,
    "num": 6360,
    "accessibility": 8,
    "race": "black_poverty",
    "label": "grocery_acc_score"
  },
  {
    "index": 25,
    "num": 10346,
    "accessibility": 8,
    "race": "black_non_poverty",
    "label": "grocery_acc_score"
  },
  {
    "index": 26,
    "num": 1435,
    "accessibility": 8,
    "race": "white_poverty",
    "label": "grocery_acc_score"
  },
  {
    "index": 27,
    "num": 11897,
    "accessibility": 8,
    "race": "white_non_poverty",
    "label": "grocery_acc_score"
  },
  {
    "index": 28,
    "num": 4461,
    "accessibility": 9,
    "race": "black_poverty",
    "label": "grocery_acc_score"
  },
  {
    "index": 29,
    "num": 15017,
    "accessibility": 9,
    "race": "black_non_poverty",
    "label": "grocery_acc_score"
  },
  {
    "index": 30,
    "num": 3215,
    "accessibility": 9,
    "race": "white_poverty",
    "label": "grocery_acc_score"
  },
  {
    "index": 31,
    "num": 29392,
    "accessibility": 9,
    "race": "white_non_poverty",
    "label": "grocery_acc_score"
  },
  {
    "index": 32,
    "num": 3970,
    "accessibility": 10,
    "race": "black_poverty",
    "label": "grocery_acc_score"
  },
  {
    "index": 33,
    "num": 9531,
    "accessibility": 10,
    "race": "black_non_poverty",
    "label": "grocery_acc_score"
  },
  {
    "index": 34,
    "num": 1588,
    "accessibility": 10,
    "race": "white_poverty",
    "label": "grocery_acc_score"
  },
  {
    "index": 35,
    "num": 12757,
    "accessibility": 10,
    "race": "white_non_poverty",
    "label": "grocery_acc_score"
  },
  {
    "index": 0,
    "num": 83,
    "accessibility": 1,
    "race": "white_poverty",
    "label": "grocery2_acc_score"
  },
  {
    "index": 1,
    "num": 1212,
    "accessibility": 1,
    "race": "white_non_poverty",
    "label": "grocery2_acc_score"
  },
  {
    "index": 2,
    "num": 6,
    "accessibility": 2,
    "race": "black_poverty",
    "label": "grocery2_acc_score"
  },
  {
    "index": 3,
    "num": 198,
    "accessibility": 2,
    "race": "black_non_poverty",
    "label": "grocery2_acc_score"
  },
  {
    "index": 4,
    "num": 352,
    "accessibility": 2,
    "race": "white_poverty",
    "label": "grocery2_acc_score"
  },
  {
    "index": 5,
    "num": 4207,
    "accessibility": 2,
    "race": "white_non_poverty",
    "label": "grocery2_acc_score"
  },
  {
    "index": 6,
    "num": 43,
    "accessibility": 3,
    "race": "black_poverty",
    "label": "grocery2_acc_score"
  },
  {
    "index": 7,
    "num": 637,
    "accessibility": 3,
    "race": "black_non_poverty",
    "label": "grocery2_acc_score"
  },
  {
    "index": 8,
    "num": 380,
    "accessibility": 3,
    "race": "white_poverty",
    "label": "grocery2_acc_score"
  },
  {
    "index": 9,
    "num": 4197,
    "accessibility": 3,
    "race": "white_non_poverty",
    "label": "grocery2_acc_score"
  },
  {
    "index": 10,
    "num": 6362,
    "accessibility": 4,
    "race": "black_poverty",
    "label": "grocery2_acc_score"
  },
  {
    "index": 11,
    "num": 8114,
    "accessibility": 4,
    "race": "black_non_poverty",
    "label": "grocery2_acc_score"
  },
  {
    "index": 12,
    "num": 939,
    "accessibility": 4,
    "race": "white_poverty",
    "label": "grocery2_acc_score"
  },
  {
    "index": 13,
    "num": 7407,
    "accessibility": 4,
    "race": "white_non_poverty",
    "label": "grocery2_acc_score"
  },
  {
    "index": 14,
    "num": 8806,
    "accessibility": 5,
    "race": "black_poverty",
    "label": "grocery2_acc_score"
  },
  {
    "index": 15,
    "num": 14414,
    "accessibility": 5,
    "race": "black_non_poverty",
    "label": "grocery2_acc_score"
  },
  {
    "index": 16,
    "num": 1053,
    "accessibility": 5,
    "race": "white_poverty",
    "label": "grocery2_acc_score"
  },
  {
    "index": 17,
    "num": 10848,
    "accessibility": 5,
    "race": "white_non_poverty",
    "label": "grocery2_acc_score"
  },
  {
    "index": 18,
    "num": 7200,
    "accessibility": 6,
    "race": "black_poverty",
    "label": "grocery2_acc_score"
  },
  {
    "index": 19,
    "num": 13795,
    "accessibility": 6,
    "race": "black_non_poverty",
    "label": "grocery2_acc_score"
  },
  {
    "index": 20,
    "num": 1230,
    "accessibility": 6,
    "race": "white_poverty",
    "label": "grocery2_acc_score"
  },
  {
    "index": 21,
    "num": 9401,
    "accessibility": 6,
    "race": "white_non_poverty",
    "label": "grocery2_acc_score"
  },
  {
    "index": 22,
    "num": 6748,
    "accessibility": 7,
    "race": "black_poverty",
    "label": "grocery2_acc_score"
  },
  {
    "index": 23,
    "num": 9686,
    "accessibility": 7,
    "race": "black_non_poverty",
    "label": "grocery2_acc_score"
  },
  {
    "index": 24,
    "num": 786,
    "accessibility": 7,
    "race": "white_poverty",
    "label": "grocery2_acc_score"
  },
  {
    "index": 25,
    "num": 3790,
    "accessibility": 7,
    "race": "white_non_poverty",
    "label": "grocery2_acc_score"
  },
  {
    "index": 26,
    "num": 4925,
    "accessibility": 8,
    "race": "black_poverty",
    "label": "grocery2_acc_score"
  },
  {
    "index": 27,
    "num": 11114,
    "accessibility": 8,
    "race": "black_non_poverty",
    "label": "grocery2_acc_score"
  },
  {
    "index": 28,
    "num": 1793,
    "accessibility": 8,
    "race": "white_poverty",
    "label": "grocery2_acc_score"
  },
  {
    "index": 29,
    "num": 20502,
    "accessibility": 8,
    "race": "white_non_poverty",
    "label": "grocery2_acc_score"
  },
  {
    "index": 30,
    "num": 4658,
    "accessibility": 9,
    "race": "black_poverty",
    "label": "grocery2_acc_score"
  },
  {
    "index": 31,
    "num": 15590,
    "accessibility": 9,
    "race": "black_non_poverty",
    "label": "grocery2_acc_score"
  },
  {
    "index": 32,
    "num": 3419,
    "accessibility": 9,
    "race": "white_poverty",
    "label": "grocery2_acc_score"
  },
  {
    "index": 33,
    "num": 25984,
    "accessibility": 9,
    "race": "white_non_poverty",
    "label": "grocery2_acc_score"
  },
  {
    "index": 34,
    "num": 522,
    "accessibility": 10,
    "race": "black_poverty",
    "label": "grocery2_acc_score"
  },
  {
    "index": 35,
    "num": 2015,
    "accessibility": 10,
    "race": "black_non_poverty",
    "label": "grocery2_acc_score"
  },
  {
    "index": 36,
    "num": 426,
    "accessibility": 10,
    "race": "white_poverty",
    "label": "grocery2_acc_score"
  },
  {
    "index": 37,
    "num": 5564,
    "accessibility": 10,
    "race": "white_non_poverty",
    "label": "grocery2_acc_score"
  },
  {
    "index": 0,
    "num": 79,
    "accessibility": 1,
    "race": "black_poverty",
    "label": "grocery2_Monday_score"
  },
  {
    "index": 1,
    "num": 873,
    "accessibility": 1,
    "race": "black_non_poverty",
    "label": "grocery2_Monday_score"
  },
  {
    "index": 2,
    "num": 911,
    "accessibility": 1,
    "race": "white_poverty",
    "label": "grocery2_Monday_score"
  },
  {
    "index": 3,
    "num": 9980,
    "accessibility": 1,
    "race": "white_non_poverty",
    "label": "grocery2_Monday_score"
  },
  {
    "index": 4,
    "num": 6506,
    "accessibility": 2,
    "race": "black_poverty",
    "label": "grocery2_Monday_score"
  },
  {
    "index": 5,
    "num": 8228,
    "accessibility": 2,
    "race": "black_non_poverty",
    "label": "grocery2_Monday_score"
  },
  {
    "index": 6,
    "num": 1044,
    "accessibility": 2,
    "race": "white_poverty",
    "label": "grocery2_Monday_score"
  },
  {
    "index": 7,
    "num": 10170,
    "accessibility": 2,
    "race": "white_non_poverty",
    "label": "grocery2_Monday_score"
  },
  {
    "index": 8,
    "num": 9510,
    "accessibility": 3,
    "race": "black_poverty",
    "label": "grocery2_Monday_score"
  },
  {
    "index": 9,
    "num": 16029,
    "accessibility": 3,
    "race": "black_non_poverty",
    "label": "grocery2_Monday_score"
  },
  {
    "index": 10,
    "num": 1238,
    "accessibility": 3,
    "race": "white_poverty",
    "label": "grocery2_Monday_score"
  },
  {
    "index": 11,
    "num": 11392,
    "accessibility": 3,
    "race": "white_non_poverty",
    "label": "grocery2_Monday_score"
  },
  {
    "index": 12,
    "num": 7828,
    "accessibility": 4,
    "race": "black_poverty",
    "label": "grocery2_Monday_score"
  },
  {
    "index": 13,
    "num": 13362,
    "accessibility": 4,
    "race": "black_non_poverty",
    "label": "grocery2_Monday_score"
  },
  {
    "index": 14,
    "num": 463,
    "accessibility": 4,
    "race": "white_poverty",
    "label": "grocery2_Monday_score"
  },
  {
    "index": 15,
    "num": 4053,
    "accessibility": 4,
    "race": "white_non_poverty",
    "label": "grocery2_Monday_score"
  },
  {
    "index": 16,
    "num": 4093,
    "accessibility": 5,
    "race": "black_poverty",
    "label": "grocery2_Monday_score"
  },
  {
    "index": 17,
    "num": 6524,
    "accessibility": 5,
    "race": "black_non_poverty",
    "label": "grocery2_Monday_score"
  },
  {
    "index": 18,
    "num": 989,
    "accessibility": 5,
    "race": "white_poverty",
    "label": "grocery2_Monday_score"
  },
  {
    "index": 19,
    "num": 4633,
    "accessibility": 5,
    "race": "white_non_poverty",
    "label": "grocery2_Monday_score"
  },
  {
    "index": 20,
    "num": 4277,
    "accessibility": 6,
    "race": "black_poverty",
    "label": "grocery2_Monday_score"
  },
  {
    "index": 21,
    "num": 7582,
    "accessibility": 6,
    "race": "black_non_poverty",
    "label": "grocery2_Monday_score"
  },
  {
    "index": 22,
    "num": 721,
    "accessibility": 6,
    "race": "white_poverty",
    "label": "grocery2_Monday_score"
  },
  {
    "index": 23,
    "num": 6641,
    "accessibility": 6,
    "race": "white_non_poverty",
    "label": "grocery2_Monday_score"
  },
  {
    "index": 24,
    "num": 2908,
    "accessibility": 7,
    "race": "black_poverty",
    "label": "grocery2_Monday_score"
  },
  {
    "index": 25,
    "num": 11823,
    "accessibility": 7,
    "race": "black_non_poverty",
    "label": "grocery2_Monday_score"
  },
  {
    "index": 26,
    "num": 1542,
    "accessibility": 7,
    "race": "white_poverty",
    "label": "grocery2_Monday_score"
  },
  {
    "index": 27,
    "num": 15704,
    "accessibility": 7,
    "race": "white_non_poverty",
    "label": "grocery2_Monday_score"
  },
  {
    "index": 28,
    "num": 3387,
    "accessibility": 8,
    "race": "black_poverty",
    "label": "grocery2_Monday_score"
  },
  {
    "index": 29,
    "num": 7584,
    "accessibility": 8,
    "race": "black_non_poverty",
    "label": "grocery2_Monday_score"
  },
  {
    "index": 30,
    "num": 2497,
    "accessibility": 8,
    "race": "white_poverty",
    "label": "grocery2_Monday_score"
  },
  {
    "index": 31,
    "num": 17545,
    "accessibility": 8,
    "race": "white_non_poverty",
    "label": "grocery2_Monday_score"
  },
  {
    "index": 32,
    "num": 629,
    "accessibility": 9,
    "race": "black_poverty",
    "label": "grocery2_Monday_score"
  },
  {
    "index": 33,
    "num": 2918,
    "accessibility": 9,
    "race": "black_non_poverty",
    "label": "grocery2_Monday_score"
  },
  {
    "index": 34,
    "num": 950,
    "accessibility": 9,
    "race": "white_poverty",
    "label": "grocery2_Monday_score"
  },
  {
    "index": 35,
    "num": 12158,
    "accessibility": 9,
    "race": "white_non_poverty",
    "label": "grocery2_Monday_score"
  },
  {
    "index": 36,
    "num": 53,
    "accessibility": 10,
    "race": "black_poverty",
    "label": "grocery2_Monday_score"
  },
  {
    "index": 37,
    "num": 640,
    "accessibility": 10,
    "race": "black_non_poverty",
    "label": "grocery2_Monday_score"
  },
  {
    "index": 38,
    "num": 106,
    "accessibility": 10,
    "race": "white_poverty",
    "label": "grocery2_Monday_score"
  },
  {
    "index": 39,
    "num": 836,
    "accessibility": 10,
    "race": "white_non_poverty",
    "label": "grocery2_Monday_score"
  },
  {
    "index": 0,
    "num": 2481,
    "accessibility": 1,
    "race": "black_poverty",
    "label": "grocery2_compete2_score"
  },
  {
    "index": 1,
    "num": 3863,
    "accessibility": 1,
    "race": "black_non_poverty",
    "label": "grocery2_compete2_score"
  },
  {
    "index": 2,
    "num": 1889,
    "accessibility": 1,
    "race": "white_poverty",
    "label": "grocery2_compete2_score"
  },
  {
    "index": 3,
    "num": 19977,
    "accessibility": 1,
    "race": "white_non_poverty",
    "label": "grocery2_compete2_score"
  },
  {
    "index": 4,
    "num": 19962,
    "accessibility": 2,
    "race": "black_poverty",
    "label": "grocery2_compete2_score"
  },
  {
    "index": 5,
    "num": 34515,
    "accessibility": 2,
    "race": "black_non_poverty",
    "label": "grocery2_compete2_score"
  },
  {
    "index": 6,
    "num": 1784,
    "accessibility": 2,
    "race": "white_poverty",
    "label": "grocery2_compete2_score"
  },
  {
    "index": 7,
    "num": 15875,
    "accessibility": 2,
    "race": "white_non_poverty",
    "label": "grocery2_compete2_score"
  },
  {
    "index": 8,
    "num": 10066,
    "accessibility": 3,
    "race": "black_poverty",
    "label": "grocery2_compete2_score"
  },
  {
    "index": 9,
    "num": 16887,
    "accessibility": 3,
    "race": "black_non_poverty",
    "label": "grocery2_compete2_score"
  },
  {
    "index": 10,
    "num": 1925,
    "accessibility": 3,
    "race": "white_poverty",
    "label": "grocery2_compete2_score"
  },
  {
    "index": 11,
    "num": 15517,
    "accessibility": 3,
    "race": "white_non_poverty",
    "label": "grocery2_compete2_score"
  },
  {
    "index": 12,
    "num": 3833,
    "accessibility": 4,
    "race": "black_poverty",
    "label": "grocery2_compete2_score"
  },
  {
    "index": 13,
    "num": 12109,
    "accessibility": 4,
    "race": "black_non_poverty",
    "label": "grocery2_compete2_score"
  },
  {
    "index": 14,
    "num": 2379,
    "accessibility": 4,
    "race": "white_poverty",
    "label": "grocery2_compete2_score"
  },
  {
    "index": 15,
    "num": 13901,
    "accessibility": 4,
    "race": "white_non_poverty",
    "label": "grocery2_compete2_score"
  },
  {
    "index": 16,
    "num": 2725,
    "accessibility": 5,
    "race": "black_poverty",
    "label": "grocery2_compete2_score"
  },
  {
    "index": 17,
    "num": 5417,
    "accessibility": 5,
    "race": "black_non_poverty",
    "label": "grocery2_compete2_score"
  },
  {
    "index": 18,
    "num": 1167,
    "accessibility": 5,
    "race": "white_poverty",
    "label": "grocery2_compete2_score"
  },
  {
    "index": 19,
    "num": 13399,
    "accessibility": 5,
    "race": "white_non_poverty",
    "label": "grocery2_compete2_score"
  },
  {
    "index": 20,
    "num": 124,
    "accessibility": 6,
    "race": "black_poverty",
    "label": "grocery2_compete2_score"
  },
  {
    "index": 21,
    "num": 2215,
    "accessibility": 6,
    "race": "black_non_poverty",
    "label": "grocery2_compete2_score"
  },
  {
    "index": 22,
    "num": 960,
    "accessibility": 6,
    "race": "white_poverty",
    "label": "grocery2_compete2_score"
  },
  {
    "index": 23,
    "num": 12293,
    "accessibility": 6,
    "race": "white_non_poverty",
    "label": "grocery2_compete2_score"
  },
  {
    "index": 24,
    "num": 79,
    "accessibility": 7,
    "race": "black_poverty",
    "label": "grocery2_compete2_score"
  },
  {
    "index": 25,
    "num": 557,
    "accessibility": 7,
    "race": "black_non_poverty",
    "label": "grocery2_compete2_score"
  },
  {
    "index": 26,
    "num": 357,
    "accessibility": 7,
    "race": "white_poverty",
    "label": "grocery2_compete2_score"
  },
  {
    "index": 27,
    "num": 2150,
    "accessibility": 7,
    "race": "white_non_poverty",
    "label": "grocery2_compete2_score"
  },
  {
    "index": 0,
    "num": 2481,
    "accessibility": 1,
    "race": "black_poverty",
    "label": "grocery2_compete1.5_score"
  },
  {
    "index": 1,
    "num": 3863,
    "accessibility": 1,
    "race": "black_non_poverty",
    "label": "grocery2_compete1.5_score"
  },
  {
    "index": 2,
    "num": 1889,
    "accessibility": 1,
    "race": "white_poverty",
    "label": "grocery2_compete1.5_score"
  },
  {
    "index": 3,
    "num": 19977,
    "accessibility": 1,
    "race": "white_non_poverty",
    "label": "grocery2_compete1.5_score"
  },
  {
    "index": 4,
    "num": 20891,
    "accessibility": 2,
    "race": "black_poverty",
    "label": "grocery2_compete1.5_score"
  },
  {
    "index": 5,
    "num": 36383,
    "accessibility": 2,
    "race": "black_non_poverty",
    "label": "grocery2_compete1.5_score"
  },
  {
    "index": 6,
    "num": 1907,
    "accessibility": 2,
    "race": "white_poverty",
    "label": "grocery2_compete1.5_score"
  },
  {
    "index": 7,
    "num": 16388,
    "accessibility": 2,
    "race": "white_non_poverty",
    "label": "grocery2_compete1.5_score"
  },
  {
    "index": 8,
    "num": 9982,
    "accessibility": 3,
    "race": "black_poverty",
    "label": "grocery2_compete1.5_score"
  },
  {
    "index": 9,
    "num": 16880,
    "accessibility": 3,
    "race": "black_non_poverty",
    "label": "grocery2_compete1.5_score"
  },
  {
    "index": 10,
    "num": 2596,
    "accessibility": 3,
    "race": "white_poverty",
    "label": "grocery2_compete1.5_score"
  },
  {
    "index": 11,
    "num": 18379,
    "accessibility": 3,
    "race": "white_non_poverty",
    "label": "grocery2_compete1.5_score"
  },
  {
    "index": 12,
    "num": 3074,
    "accessibility": 4,
    "race": "black_poverty",
    "label": "grocery2_compete1.5_score"
  },
  {
    "index": 13,
    "num": 11035,
    "accessibility": 4,
    "race": "black_non_poverty",
    "label": "grocery2_compete1.5_score"
  },
  {
    "index": 14,
    "num": 2200,
    "accessibility": 4,
    "race": "white_poverty",
    "label": "grocery2_compete1.5_score"
  },
  {
    "index": 15,
    "num": 16829,
    "accessibility": 4,
    "race": "white_non_poverty",
    "label": "grocery2_compete1.5_score"
  },
  {
    "index": 16,
    "num": 2690,
    "accessibility": 5,
    "race": "black_poverty",
    "label": "grocery2_compete1.5_score"
  },
  {
    "index": 17,
    "num": 5559,
    "accessibility": 5,
    "race": "black_non_poverty",
    "label": "grocery2_compete1.5_score"
  },
  {
    "index": 18,
    "num": 1358,
    "accessibility": 5,
    "race": "white_poverty",
    "label": "grocery2_compete1.5_score"
  },
  {
    "index": 19,
    "num": 15738,
    "accessibility": 5,
    "race": "white_non_poverty",
    "label": "grocery2_compete1.5_score"
  },
  {
    "index": 20,
    "num": 126,
    "accessibility": 6,
    "race": "black_poverty",
    "label": "grocery2_compete1.5_score"
  },
  {
    "index": 21,
    "num": 1720,
    "accessibility": 6,
    "race": "black_non_poverty",
    "label": "grocery2_compete1.5_score"
  },
  {
    "index": 22,
    "num": 408,
    "accessibility": 6,
    "race": "white_poverty",
    "label": "grocery2_compete1.5_score"
  },
  {
    "index": 23,
    "num": 5317,
    "accessibility": 6,
    "race": "white_non_poverty",
    "label": "grocery2_compete1.5_score"
  },
  {
    "index": 24,
    "num": 26,
    "accessibility": 7,
    "race": "black_poverty",
    "label": "grocery2_compete1.5_score"
  },
  {
    "index": 25,
    "num": 123,
    "accessibility": 7,
    "race": "black_non_poverty",
    "label": "grocery2_compete1.5_score"
  },
  {
    "index": 26,
    "num": 103,
    "accessibility": 7,
    "race": "white_poverty",
    "label": "grocery2_compete1.5_score"
  },
  {
    "index": 27,
    "num": 484,
    "accessibility": 7,
    "race": "white_non_poverty",
    "label": "grocery2_compete1.5_score"
  }
]